src/__init__.py
fastmcpclient-0.0.1.dist-info/METADATA
fastmcpclient-0.0.1.dist-info/WHEEL
fastmcpclient-0.0.1.dist-info/top_level.txt
fastmcpclient-0.0.1.dist-info/RECORD
