Metadata-Version: 2.4
Name: fastmcpclient
Version: 0.0.1
Summary: Python client, based on fastmcp, for connecting to MCP servers through multiple protocols, specifically designed to work with integrated language models.
Home-page: https://github.com/rb58853/python-mcp-client
Author: Raúl Beltrán Gómez
Author-email: rb58853@gmail.com
License: MIT
Classifier: Programming Language :: Python :: 3
Classifier: Operating System :: OS Independent
Requires-Python: >=3.11
Dynamic: author
Dynamic: author-email
Dynamic: classifier
Dynamic: description
Dynamic: description-content-type
Dynamic: home-page
Dynamic: license
Dynamic: requires-python
Dynamic: summary
